androset.py
androset-1.1.dist-info/LICENSE
androset-1.1.dist-info/METADATA
androset-1.1.dist-info/WHEEL
androset-1.1.dist-info/entry_points.txt
androset-1.1.dist-info/top_level.txt
androset-1.1.dist-info/RECORD
