Metadata-Version: 2.1
Name: androset
Version: 1.1
Summary: Auto setup android for pentest with auto push burp certificate and redirect traffic to burp with IP Table
Home-page: https://github.com/Anof-cyber/androset
Download-URL: https://github.com/Anof-cyber/androset/archive/v1.1.zip
Author: Sourav Kalal
Author-email: kalalsourav20@gmail.com
License: MIT license
Keywords: androset,bug bounty,android,pentesting,security
Classifier: Development Status :: 5 - Production/Stable
Classifier: Intended Audience :: Developers
Classifier: Intended Audience :: Information Technology
Classifier: Operating System :: OS Independent
Classifier: Topic :: Security
Classifier: License :: OSI Approved :: MIT License
Classifier: Programming Language :: Python :: 3.4
Requires-Python: >=3.6
License-File: LICENSE
Requires-Dist: pyOpenSSL (==23.1.1)
Requires-Dist: termcolor (==2.3.0)
